odoo10_addon_hr_citizenship-10.0.1.0.0.99.dev4-py3.8-nspkg.pth
odoo/addons/hr_citizenship/README.rst
odoo/addons/hr_citizenship/__init__.py
odoo/addons/hr_citizenship/__manifest__.py
odoo/addons/hr_citizenship/i18n/hr_citizenship.pot
odoo/addons/hr_citizenship/models/__init__.py
odoo/addons/hr_citizenship/models/hr_applicant.py
odoo/addons/hr_citizenship/models/hr_employee.py
odoo/addons/hr_citizenship/models/res_citizenship.py
odoo/addons/hr_citizenship/readme/CONTRIBUTORS.rst
odoo/addons/hr_citizenship/readme/DESCRIPTION.rst
odoo/addons/hr_citizenship/security/ir.model.access.csv
odoo/addons/hr_citizenship/security/res_groups.xml
odoo/addons/hr_citizenship/static/description/icon.png
odoo/addons/hr_citizenship/static/description/index.html
odoo/addons/hr_citizenship/tests/__init__.py
odoo/addons/hr_citizenship/tests/test_citizenship.py
odoo/addons/hr_citizenship/views/hr_applicant.xml
odoo/addons/hr_citizenship/views/hr_employee.xml
odoo10_addon_hr_citizenship-10.0.1.0.0.99.dev4.dist-info/METADATA
odoo10_addon_hr_citizenship-10.0.1.0.0.99.dev4.dist-info/WHEEL
odoo10_addon_hr_citizenship-10.0.1.0.0.99.dev4.dist-info/namespace_packages.txt
odoo10_addon_hr_citizenship-10.0.1.0.0.99.dev4.dist-info/top_level.txt
odoo10_addon_hr_citizenship-10.0.1.0.0.99.dev4.dist-info/RECORD
